dir_magic/__init__.py
dir_magic/__main__.py
dir_magic/dirMagic.py
dir_magic/header.py
dir_magic-1.2.0.dist-info/LICENSE
dir_magic-1.2.0.dist-info/METADATA
dir_magic-1.2.0.dist-info/WHEEL
dir_magic-1.2.0.dist-info/entry_points.txt
dir_magic-1.2.0.dist-info/RECORD
