Metadata-Version: 2.1
Name: dir-magic
Version: 1.2.0
Summary: DirMagic is a library written in Python to brute force directories and subdomains
Home-page: https://github.com/heroesofcode/DirMagic
License: MIT
Author: João Lucas
Author-email: joaolucasfp2001@gmail.com
Requires-Python: >=3.10,<4.0
Classifier: Environment :: Console
Classifier: License :: OSI Approved :: MIT License
Classifier: Operating System :: OS Independent
Classifier: Programming Language :: Python :: 3
Classifier: Programming Language :: Python :: 3.10
Classifier: Programming Language :: Python :: 3.11
Classifier: Programming Language :: Python :: 3.12
Classifier: Programming Language :: Python :: 3.13
Requires-Dist: dnspython (>=2.7.0,<3.0.0)
Requires-Dist: requests (>=2.32.3,<3.0.0)
Requires-Dist: rich (>=13.9.4,<14.0.0)
Project-URL: Repository, https://github.com/heroesofcode/DirMagic
